{
  "overallScore": 64.7,
  "subscores": {
    "energyIntensity": 100,
    "waterEfficiency": 81.2,
    "chemicalLoad": 90.2,
    "stressManagement": 48.5,
    "precisionAdoption": 3.7
  },
  "weakestCategory": "precision Adoption",
  "strongestCategory": "energyIntensity",
  "weakestScore": 3.7,
  "strongestScore": 100,
  "farm": {
    "farmName": "BC Harvest 8 \u00b7 GH017 \u00b7 P0061",
    "region": "Langley",
    "climateZone": "Coastal",
    "primaryCrop": "Strawberry"
  },
  "benchmarks": {
    "energyPerKg": 0.447,
    "waterPerKg": 0.363
  },
  "moistureTrend": [
    {
      "week": "2025-02-10/2025-02-16",
      "substrate_moisture": 0.4379332664460081
    },
    {
      "week": "2025-02-17/2025-02-23",
      "substrate_moisture": 0.4877267688138609
    },
    {
      "week": "2025-02-24/2025-03-02",
      "substrate_moisture": 0.42548583953403957
    },
    {
      "week": "2025-03-03/2025-03-09",
      "substrate_moisture": 0.48441888744959805
    },
    {
      "week": "2025-03-10/2025-03-16",
      "substrate_moisture": 0.4779472620565128
    },
    {
      "week": "2025-03-17/2025-03-23",
      "substrate_moisture": 0.4058770391521209
    },
    {
      "week": "2025-03-24/2025-03-30",
      "substrate_moisture": 0.47929190783807546
    },
    {
      "week": "2025-03-31/2025-04-06",
      "substrate_moisture": 0.4162087292779351
    },
    {
      "week": "2025-04-07/2025-04-13",
      "substrate_moisture": 0.43736269116135695
    },
    {
      "week": "2025-04-14/2025-04-20",
      "substrate_moisture": 0.46348611109197524
    },
    {
      "week": "2025-04-21/2025-04-27",
      "substrate_moisture": 0.40812239587310983
    },
    {
      "week": "2025-04-28/2025-05-04",
      "substrate_moisture": 0.5007995401464759
    },
    {
      "week": "2025-05-05/2025-05-11",
      "substrate_moisture": 0.43340018263917174
    },
    {
      "week": "2025-05-12/2025-05-18",
      "substrate_moisture": 0.4621600038018024
    },
    {
      "week": "2025-05-19/2025-05-25",
      "substrate_moisture": 0.5306299263897719
    },
    {
      "week": "2025-05-26/2025-06-01",
      "substrate_moisture": 0.39826690874700627
    },
    {
      "week": "2025-06-02/2025-06-08",
      "substrate_moisture": 0.46558519377499535
    },
    {
      "week": "2025-06-09/2025-06-15",
      "substrate_moisture": 0.4440105884095481
    },
    {
      "week": "2025-06-16/2025-06-22",
      "substrate_moisture": 0.4205110949720133
    },
    {
      "week": "2025-06-23/2025-06-29",
      "substrate_moisture": 0.4781188356568538
    },
    {
      "week": "2025-06-30/2025-07-06",
      "substrate_moisture": 0.4070321979452888
    },
    {
      "week": "2025-07-07/2025-07-13",
      "substrate_moisture": 0.5027085777416593
    },
    {
      "week": "2025-07-14/2025-07-20",
      "substrate_moisture": 0.45411035228133423
    },
    {
      "week": "2025-07-21/2025-07-27",
      "substrate_moisture": 0.43916445443353236
    },
    {
      "week": "2025-07-28/2025-08-03",
      "substrate_moisture": 0.49645753223680816
    },
    {
      "week": "2025-08-04/2025-08-10",
      "substrate_moisture": 0.42964226170491643
    },
    {
      "week": "2025-08-11/2025-08-17",
      "substrate_moisture": 0.43734993217368606
    },
    {
      "week": "2025-08-18/2025-08-24",
      "substrate_moisture": 0.4735219769081522
    },
    {
      "week": "2025-08-25/2025-08-31",
      "substrate_moisture": 0.3969942799129624
    },
    {
      "week": "2025-09-01/2025-09-07",
      "substrate_moisture": 0.47287378903034377
    },
    {
      "week": "2025-09-08/2025-09-14",
      "substrate_moisture": 0.43564303636241963
    }
  ],
  "risks": [
    {
      "id": "heatwave",
      "icon": "thermometer",
      "title": "Heatwave Risk",
      "level": "healthy",
      "oneliner": "Interior farms logged 0 readings above 32\u00b0C this season"
    },
    {
      "id": "pest",
      "icon": "bug",
      "title": "Pest Outbreak",
      "level": "warning",
      "oneliner": "Pest pressure index averaging 0.43 across plots"
    },
    {
      "id": "disease",
      "icon": "shield-alert",
      "title": "Disease Spread",
      "level": "healthy",
      "oneliner": "Coastal and Fraser Valley plots show elevated disease risk indices"
    },
    {
      "id": "water",
      "icon": "droplet",
      "title": "Water Stress",
      "level": "warning",
      "oneliner": "0 plot-days experienced chronic under-irrigation"
    },
    {
      "id": "costs",
      "icon": "trending-up",
      "title": "Input Cost Volatility",
      "level": "warning",
      "oneliner": "Fertilizer prices swung 44.5% this season"
    }
  ],
  "controlBaseline": {
    "energyIntensity": 90.0,
    "waterEfficiency": 73.1,
    "chemicalLoad": 81.2,
    "stressManagement": 43.6,
    "precisionAdoption": 3.3
  }
}