{
  "overallScore": 72.1,
  "subscores": {
    "energyIntensity": 100,
    "waterEfficiency": 100,
    "chemicalLoad": 90.2,
    "stressManagement": 55.3,
    "precisionAdoption": 14.9
  },
  "weakestCategory": "precision Adoption",
  "strongestCategory": "energyIntensity",
  "weakestScore": 14.9,
  "strongestScore": 100,
  "farm": {
    "farmName": "BC Harvest 1 \u00b7 GH020 \u00b7 P0092",
    "region": "Chilliwack",
    "climateZone": "Coastal",
    "primaryCrop": "Tomato"
  },
  "benchmarks": {
    "energyPerKg": 0.128,
    "waterPerKg": 0.095
  },
  "moistureTrend": [
    {
      "week": "2025-02-10/2025-02-16",
      "substrate_moisture": 0.49463177472495445
    },
    {
      "week": "2025-02-17/2025-02-23",
      "substrate_moisture": 0.5278328470979778
    },
    {
      "week": "2025-02-24/2025-03-02",
      "substrate_moisture": 0.4539800524372076
    },
    {
      "week": "2025-03-03/2025-03-09",
      "substrate_moisture": 0.49163134144827947
    },
    {
      "week": "2025-03-10/2025-03-16",
      "substrate_moisture": 0.503681277419901
    },
    {
      "week": "2025-03-17/2025-03-23",
      "substrate_moisture": 0.45495676305643873
    },
    {
      "week": "2025-03-24/2025-03-30",
      "substrate_moisture": 0.5312975612015238
    },
    {
      "week": "2025-03-31/2025-04-06",
      "substrate_moisture": 0.4458066372540917
    },
    {
      "week": "2025-04-07/2025-04-13",
      "substrate_moisture": 0.47387118652366716
    },
    {
      "week": "2025-04-14/2025-04-20",
      "substrate_moisture": 0.4957209530267866
    },
    {
      "week": "2025-04-21/2025-04-27",
      "substrate_moisture": 0.4445575825850736
    },
    {
      "week": "2025-04-28/2025-05-04",
      "substrate_moisture": 0.508542359882512
    },
    {
      "week": "2025-05-05/2025-05-11",
      "substrate_moisture": 0.45300523514348406
    },
    {
      "week": "2025-05-12/2025-05-18",
      "substrate_moisture": 0.4502928417412022
    },
    {
      "week": "2025-05-19/2025-05-25",
      "substrate_moisture": 0.5359385471077664
    },
    {
      "week": "2025-05-26/2025-06-01",
      "substrate_moisture": 0.4663334320903761
    },
    {
      "week": "2025-06-02/2025-06-08",
      "substrate_moisture": 0.4909658053710975
    },
    {
      "week": "2025-06-09/2025-06-15",
      "substrate_moisture": 0.4433906451918316
    },
    {
      "week": "2025-06-16/2025-06-22",
      "substrate_moisture": 0.47085169178285907
    },
    {
      "week": "2025-06-23/2025-06-29",
      "substrate_moisture": 0.5349494672750246
    },
    {
      "week": "2025-06-30/2025-07-06",
      "substrate_moisture": 0.45087543269991454
    },
    {
      "week": "2025-07-07/2025-07-13",
      "substrate_moisture": 0.5059191146027302
    },
    {
      "week": "2025-07-14/2025-07-20",
      "substrate_moisture": 0.4757620112721047
    },
    {
      "week": "2025-07-21/2025-07-27",
      "substrate_moisture": 0.4675294805150606
    },
    {
      "week": "2025-07-28/2025-08-03",
      "substrate_moisture": 0.5141289183542591
    },
    {
      "week": "2025-08-04/2025-08-10",
      "substrate_moisture": 0.47181039515002654
    },
    {
      "week": "2025-08-11/2025-08-17",
      "substrate_moisture": 0.46393679121393644
    },
    {
      "week": "2025-08-18/2025-08-24",
      "substrate_moisture": 0.5025292603441296
    },
    {
      "week": "2025-08-25/2025-08-31",
      "substrate_moisture": 0.45288828728047476
    },
    {
      "week": "2025-09-01/2025-09-07",
      "substrate_moisture": 0.5325041561701279
    },
    {
      "week": "2025-09-08/2025-09-14",
      "substrate_moisture": 0.489173622999156
    }
  ],
  "risks": [
    {
      "id": "heatwave",
      "icon": "thermometer",
      "title": "Heatwave Risk",
      "level": "healthy",
      "oneliner": "Interior farms logged 0 readings above 32\u00b0C this season"
    },
    {
      "id": "pest",
      "icon": "bug",
      "title": "Pest Outbreak",
      "level": "warning",
      "oneliner": "Pest pressure index averaging 0.43 across plots"
    },
    {
      "id": "disease",
      "icon": "shield-alert",
      "title": "Disease Spread",
      "level": "healthy",
      "oneliner": "Coastal and Fraser Valley plots show elevated disease risk indices"
    },
    {
      "id": "water",
      "icon": "droplet",
      "title": "Water Stress",
      "level": "warning",
      "oneliner": "0 plot-days experienced chronic under-irrigation"
    },
    {
      "id": "costs",
      "icon": "trending-up",
      "title": "Input Cost Volatility",
      "level": "warning",
      "oneliner": "Fertilizer prices swung 44.5% this season"
    }
  ],
  "controlBaseline": {
    "energyIntensity": 90.0,
    "waterEfficiency": 90.0,
    "chemicalLoad": 81.2,
    "stressManagement": 49.8,
    "precisionAdoption": 13.4
  }
}